stewbeet/__init__.py
stewbeet/__init__.pyi
stewbeet/__main__.py
stewbeet/all.py
stewbeet/all.pyi
stewbeet/cli.py
stewbeet/cli.pyi
stewbeet/continuous_delivery/__init__.py
stewbeet/continuous_delivery/__init__.pyi
stewbeet/continuous_delivery/cd_utils.py
stewbeet/continuous_delivery/cd_utils.pyi
stewbeet/continuous_delivery/github.py
stewbeet/continuous_delivery/github.pyi
stewbeet/continuous_delivery/modrinth.py
stewbeet/continuous_delivery/modrinth.pyi
stewbeet/continuous_delivery/pmc.py
stewbeet/continuous_delivery/pmc.pyi
stewbeet/continuous_delivery/smithed.py
stewbeet/continuous_delivery/smithed.pyi
stewbeet/contrib/simplenergy/__init__.py
stewbeet/contrib/simplenergy/balancing.py
stewbeet/contrib/simplenergy/batteries.py
stewbeet/contrib/simplenergy/cables.py
stewbeet/contrib/simplenergy/energy_cable_models/variant.json
stewbeet/contrib/simplenergy/energy_cable_models/variant_d.json
stewbeet/contrib/simplenergy/energy_cable_models/variant_de.json
stewbeet/contrib/simplenergy/energy_cable_models/variant_dew.json
stewbeet/contrib/simplenergy/energy_cable_models/variant_dn.json
stewbeet/contrib/simplenergy/energy_cable_models/variant_dne.json
stewbeet/contrib/simplenergy/energy_cable_models/variant_dnew.json
stewbeet/contrib/simplenergy/energy_cable_models/variant_dns.json
stewbeet/contrib/simplenergy/energy_cable_models/variant_dnse.json
stewbeet/contrib/simplenergy/energy_cable_models/variant_dnsew.json
stewbeet/contrib/simplenergy/energy_cable_models/variant_dnsw.json
stewbeet/contrib/simplenergy/energy_cable_models/variant_dnw.json
stewbeet/contrib/simplenergy/energy_cable_models/variant_ds.json
stewbeet/contrib/simplenergy/energy_cable_models/variant_dse.json
stewbeet/contrib/simplenergy/energy_cable_models/variant_dsew.json
stewbeet/contrib/simplenergy/energy_cable_models/variant_dsw.json
stewbeet/contrib/simplenergy/energy_cable_models/variant_dw.json
stewbeet/contrib/simplenergy/energy_cable_models/variant_e.json
stewbeet-3.0.0b11.dist-info/WHEEL
stewbeet-3.0.0b11.dist-info/entry_points.txt
stewbeet-3.0.0b11.dist-info/METADATA
stewbeet-3.0.0b11.dist-info/RECORD
