Metadata-Version: 2.4
Name: stewbeet
Version: 3.0.0b11
Summary: Beet Framework made to help generating advanced Minecraft datapack contents
Author: Stoupy51
Author-email: Stoupy51 <stoupy51@gmail.com>
License-Expression: MIT
Classifier: Programming Language :: Python :: 3
Classifier: Programming Language :: Python :: 3.14
Classifier: License :: OSI Approved :: MIT License
Classifier: Operating System :: OS Independent
Requires-Dist: stouputils>=1.14.2
Requires-Dist: model-resolver>=1.13.0
Requires-Dist: beet>=0.113.0b10
Requires-Dist: bolt>=0.50.0b5
Requires-Dist: mecha>=0.102.0b2
Requires-Dist: mutagen>=1.47.0
Requires-Dist: pyperclip>=1.8.0
Requires-Dist: smithed
Requires-Python: >=3.14
Project-URL: Homepage, https://github.com/Stoupy51/stewbeet
Project-URL: Issues, https://github.com/Stoupy51/stewbeet/issues
